tap_dune/__init__.py
tap_dune/streams.py
tap_dune/tap.py
tap_dune-1.0.0.dist-info/METADATA
tap_dune-1.0.0.dist-info/WHEEL
tap_dune-1.0.0.dist-info/entry_points.txt
tap_dune-1.0.0.dist-info/RECORD
