Metadata-Version: 2.3
Name: tap-dune
Version: 1.0.0
Summary: Singer tap for extracting data from Dune Analytics API
License: Apache-2.0
Keywords: singer,tap,dune,analytics,meltano
Author: Blueprint Data
Requires-Python: >=3.9,<4.0
Classifier: Development Status :: 4 - Beta
Classifier: Intended Audience :: Developers
Classifier: License :: OSI Approved :: Apache Software License
Classifier: Programming Language :: Python :: 3
Classifier: Programming Language :: Python :: 3.9
Classifier: Programming Language :: Python :: 3.10
Classifier: Programming Language :: Python :: 3.11
Classifier: Programming Language :: Python :: 3.12
Classifier: Programming Language :: Python :: 3.13
Requires-Dist: requests (>=2.31.0,<3.0.0)
Requires-Dist: singer-sdk (>=0.48.0,<0.49.0)
Project-URL: Homepage, https://github.com/blueprint-data/tap-dune
Project-URL: Repository, https://github.com/blueprint-data/tap-dune
